mitosheet_private/__init__.py
mitosheet_private-0.3.0.dist-info/LICENSE
mitosheet_private-0.3.0.dist-info/METADATA
mitosheet_private-0.3.0.dist-info/WHEEL
mitosheet_private-0.3.0.dist-info/top_level.txt
mitosheet_private-0.3.0.dist-info/RECORD
